codesigs/__init__.py
codesigs/_modidx.py
codesigs/core.py
codesigs-0.0.1.dist-info/licenses/LICENSE
codesigs-0.0.1.dist-info/METADATA
codesigs-0.0.1.dist-info/WHEEL
codesigs-0.0.1.dist-info/entry_points.txt
codesigs-0.0.1.dist-info/top_level.txt
codesigs-0.0.1.dist-info/RECORD
